docs/Makefile
docs/conf.py
docs/index.md
docs/make.bat
docs/_templates/autoapi/index.rst
omnisolver/pt/__init__.py
omnisolver/pt/algorithm.py
omnisolver/pt/bqm_tools.py
omnisolver/pt/model.py
omnisolver/pt/pt.yml
omnisolver/pt/replica.py
omnisolver/pt/sampler.py
omnisolver/pt/testing.py
omnisolver_pt-0.0.2.dist-info/LICENSE
omnisolver_pt-0.0.2.dist-info/METADATA
omnisolver_pt-0.0.2.dist-info/WHEEL
omnisolver_pt-0.0.2.dist-info/entry_points.txt
omnisolver_pt-0.0.2.dist-info/top_level.txt
omnisolver_pt-0.0.2.dist-info/RECORD
