Metadata-Version: 2.1
Name: omnisolver-pt
Version: 0.0.2
Summary: Parallel-tempering solver compatible with omnisolver.
Author-email: Konrad Jałowiecki <dexter2206@gmail.com>, Łukasz Pawela <lukasz.pawela@gmail.com>
License: Apache-2.0
Project-URL: repository, https://github.com/euro-hpc-pl/omnisolver-pt
Classifier: Intended Audience :: Other Audience
Classifier: Intended Audience :: Science/Research
Classifier: License :: OSI Approved :: Apache Software License
Classifier: Programming Language :: Python :: 3
Classifier: Topic :: Scientific/Engineering :: Physics
Requires-Python: >=3.8
License-File: LICENSE
Requires-Dist: omnisolver (~=0.0.3)
Requires-Dist: numba (~=0.56.4)
Requires-Dist: pluggy (~=0.13.1)
Requires-Dist: numpy (~=1.19.4)
Provides-Extra: docs
Requires-Dist: sphinx (~=6.1.3) ; extra == 'docs'
Requires-Dist: sphinx-autoapi (~=2.0.1) ; extra == 'docs'
Requires-Dist: pydata-sphinx-theme (~=0.13.1) ; extra == 'docs'
Requires-Dist: sphinx-term (~=0.1) ; extra == 'docs'
Requires-Dist: myst-parser (~=1.0.0) ; extra == 'docs'
Provides-Extra: test
Requires-Dist: pytest (>=6.1.2) ; extra == 'test'
Requires-Dist: pytest-mock (>=3.3.1) ; extra == 'test'
Requires-Dist: pytest-cov[toml] (>=2.12.1) ; extra == 'test'
